{
  "fall_9.000": "Erm... Dokter Harvey? Ini rahasia ya kan?",
  "15.000": "Aku suka memeriksa perkembangan bisnis lokal dan melihat bagaimana keadaannya.",
  "6.000": "Aku di sini untuk mengumpulkan pajak bisnis Clint.",
  "1.000": "Nah, ikan pasti harum segar musim ini.",
  "Tue.000": "Aku melakukan semua belanja kelontongku di sini.$h",
  "3.000": "Aku di sini cuman untuk memastikan semua kebutuhan bisnis Marnie terpenuhi.",
  "6.001": "Perpustakaan adalah salah satu fitur terbaik Pelican Town. Ini didanai dengan pajak yang kami kumpulkan dari bisnis lokal.",
  "winter_16.000": "Tahu kan, aku telah membeli beberapa barang favoritku dari pasar ini..."
}